{
  "action": {
    "description": "Subcommittee recommends passage.",
    "occurred_at": "2025-03-12",
    "jurisdiction_id": "~{\"classification\": \"legislature\"}",
    "session_id": "2025-2026",
    "entity_type": "bill",
    "classifications": [
      "committee-passage-favorable"
    ],
    "related_entities": [],
    "sources": [
      {
        "url": "https://www.legis.iowa.gov/legislation/billTracking/billHistory?billName=HSB 225&ga=91",
        "note": ""
      }
    ]
  },
  "bill_id": "HSB 225"
}